{"briefing":[{"category":"briefingEvent","eventName":"displayBriefingStep","itemID":1,"timeOfEvent":1601386319698,"eventDuration":0},{"category":"briefingEvent","eventName":"displayBriefingStep","itemID":2,"timeOfEvent":1601386329456,"eventDuration":0},{"category":"briefingEvent","eventName":"displayBriefingStep","itemID":3,"timeOfEvent":1601386333717,"eventDuration":0},{"category":"briefingEvent","eventName":"displayBriefingStep","itemID":4,"timeOfEvent":1601386335621,"eventDuration":0},{"category":"briefingEvent","eventName":"displayBriefingStep","itemID":5,"timeOfEvent":1601386336610,"eventDuration":0},{"category":"briefingEvent","eventName":"displayBriefingStep","itemID":6,"timeOfEvent":1601386339040,"eventDuration":0},{"category":"timeStamps","eventName":"briefingDuration","itemID":"none","timeOfEvent":1601386370265,"eventDuration":null}],"ranking":[{"category":"serverEvent","eventName":"loadNewRankingType","itemID":1,"timeOfEvent":1601386373920,"eventDuration":0},{"category":"rankingRepresentation","timeOfEvent":1601386373920,"ranking":[{"id":40,"name":"Cynthia Scott","score":0.8371873144904489,"tag1":"100%","tag2":100,"tag3":48,"gender":"f","fairrank":10,"scorerank":9,"rank":1},{"id":39,"name":"Angela Taylor","score":0.8384138632702831,"tag1":"100%","tag2":98,"tag3":458,"gender":"f","fairrank":9,"scorerank":8,"rank":2},{"id":38,"name":"Jennifer Thomas","score":0.8466832462421382,"tag1":"98%","tag2":100,"tag3":388,"gender":"f","fairrank":8,"scorerank":6,"rank":3},{"id":34,"name":"Paul Allen","score":0.839492387045522,"tag1":"100%","tag2":100,"tag3":141,"gender":"m","fairrank":4,"scorerank":7,"rank":4},{"id":35,"name":"Lisa Cook","score":0.8502374704583605,"tag1":"100%","tag2":100,"tag3":64,"gender":"f","fairrank":5,"scorerank":3,"rank":5},{"id":31,"name":"Michelle Martin","score":0.8685688011573159,"tag1":"99%","tag2":100,"tag3":634,"gender":"f","fairrank":1,"scorerank":1,"rank":6},{"id":33,"name":"Patricia Thomas","score":0.8590045381474498,"tag1":"97%","tag2":100,"tag3":395,"gender":"f","fairrank":3,"scorerank":2,"rank":7},{"id":36,"name":"Daniel Campbell","score":0.8339155032920075,"tag1":"99%","tag2":100,"tag3":7,"gender":"m","fairrank":6,"scorerank":10,"rank":8},{"id":37,"name":"Linda Taylor","score":0.8481191210673654,"tag1":"100%","tag2":100,"tag3":158,"gender":"f","fairrank":7,"scorerank":5,"rank":9},{"id":32,"name":"Joseph Clark","score":0.8484922997440333,"tag1":"100%","tag2":100,"tag3":41,"gender":"m","fairrank":2,"scorerank":4,"rank":10}]},{"category":"mouseEvent","eventName":"firstHover","itemID":37,"timeOfEvent":1601386428809,"eventDuration":152},{"category":"mouseEvent","eventName":"firstHover","itemID":37,"timeOfEvent":1601386428892,"eventDuration":67},{"category":"mouseEvent","eventName":"firstHover","itemID":33,"timeOfEvent":1601386429076,"eventDuration":134},{"category":"mouseEvent","eventName":"firstHover","itemID":37,"timeOfEvent":1601386429109,"eventDuration":17},{"category":"mouseEvent","eventName":"firstHover","itemID":37,"timeOfEvent":1601386429359,"eventDuration":82},{"category":"mouseEvent","eventName":"firstHover","itemID":33,"timeOfEvent":1601386429408,"eventDuration":31},{"category":"mouseEvent","eventName":"firstHover","itemID":35,"timeOfEvent":1601386429826,"eventDuration":400},{"category":"mouseEvent","eventName":"firstHover","itemID":38,"timeOfEvent":1601386429975,"eventDuration":116},{"category":"mouseEvent","eventName":"select","itemID":38,"timeOfEvent":1601386432825,"eventDuration":0},{"category":"mouseEvent","eventName":"longHover","itemID":38,"timeOfEvent":1601386436342,"eventDuration":6334},{"category":"mouseEvent","eventName":"firstHover","itemID":34,"timeOfEvent":1601386436808,"eventDuration":465},{"category":"mouseEvent","eventName":"firstHover","itemID":39,"timeOfEvent":1601386437875,"eventDuration":575},{"category":"mouseEvent","eventName":"firstHover","itemID":40,"timeOfEvent":1601386438758,"eventDuration":882},{"category":"mouseEvent","eventName":"firstHover","itemID":38,"timeOfEvent":1601386438792,"eventDuration":17},{"category":"mouseEvent","eventName":"longHover","itemID":35,"timeOfEvent":1601386440808,"eventDuration":2000},{"category":"mouseEvent","eventName":"select","itemID":33,"timeOfEvent":1601386441648,"eventDuration":0},{"category":"mouseEvent","eventName":"firstHover","itemID":33,"timeOfEvent":1601386442175,"eventDuration":1367},{"category":"mouseEvent","eventName":"firstHover","itemID":36,"timeOfEvent":1601386442209,"eventDuration":34},{"category":"mouseEvent","eventName":"firstHover","itemID":32,"timeOfEvent":1601386443579,"eventDuration":35},{"category":"mouseEvent","eventName":"firstHover","itemID":36,"timeOfEvent":1601386443692,"eventDuration":113},{"category":"mouseEvent","eventName":"firstHover","itemID":33,"timeOfEvent":1601386443775,"eventDuration":67},{"category":"mouseEvent","eventName":"select","itemID":37,"timeOfEvent":1601386444632,"eventDuration":0},{"category":"mouseEvent","eventName":"firstHover","itemID":37,"timeOfEvent":1601386445075,"eventDuration":966},{"category":"mouseEvent","eventName":"firstHover","itemID":33,"timeOfEvent":1601386445126,"eventDuration":31},{"category":"mouseEvent","eventName":"select","itemID":35,"timeOfEvent":1601386445580,"eventDuration":0},{"category":"mouseEvent","eventName":"firstHover","itemID":35,"timeOfEvent":1601386445958,"eventDuration":815},{"category":"serverEvent","eventName":"loadNewRankingType","itemID":1,"timeOfEvent":1601386454296,"eventDuration":0},{"category":"rankingRepresentation","timeOfEvent":1601386454296,"ranking":[{"id":15,"name":"Lisa Phillips","score":0.7805555452827792,"tag1":"100%","tag2":78,"tag3":0,"gender":"f","fairrank":5,"scorerank":3,"rank":1},{"id":18,"name":"Elizabeth Davis","score":0.742341028683199,"tag1":"100%","tag2":100,"tag3":6,"gender":"f","fairrank":8,"scorerank":5,"rank":2},{"id":16,"name":"Gary Roberts","score":0.7030471958586693,"tag1":"100%","tag2":100,"tag3":3,"gender":"m","fairrank":6,"scorerank":10,"rank":3},{"id":13,"name":"Angela Green","score":0.788158103114649,"tag1":"98%","tag2":100,"tag3":1,"gender":"f","fairrank":3,"scorerank":2,"rank":4},{"id":17,"name":"Mary White","score":0.7710606362667689,"tag1":"98%","tag2":100,"tag3":0,"gender":"f","fairrank":7,"scorerank":4,"rank":5},{"id":19,"name":"Ashley Scott","score":0.7375636107859171,"tag1":"97%","tag2":100,"tag3":2,"gender":"f","fairrank":9,"scorerank":7,"rank":6},{"id":14,"name":"Stephen Moore","score":0.7258889517568552,"tag1":"93%","tag2":100,"tag3":2,"gender":"m","fairrank":4,"scorerank":8,"rank":7},{"id":12,"name":"Joshua Thomas","score":0.7412400221038719,"tag1":"98%","tag2":100,"tag3":10,"gender":"m","fairrank":2,"scorerank":6,"rank":8},{"id":20,"name":"Amanda Collins","score":0.719530008545884,"tag1":"99%","tag2":100,"tag3":2,"gender":"f","fairrank":10,"scorerank":9,"rank":9},{"id":11,"name":"Sarah Hill","score":0.799641978367866,"tag1":"95%","tag2":96,"tag3":0,"gender":"f","fairrank":1,"scorerank":1,"rank":10}]},{"category":"mouseEvent","eventName":"firstHover","itemID":14,"timeOfEvent":1601386455825,"eventDuration":451},{"category":"mouseEvent","eventName":"firstHover","itemID":17,"timeOfEvent":1601386455907,"eventDuration":65},{"category":"mouseEvent","eventName":"firstHover","itemID":19,"timeOfEvent":1601386456257,"eventDuration":349},{"category":"mouseEvent","eventName":"firstHover","itemID":18,"timeOfEvent":1601386459508,"eventDuration":564},{"category":"mouseEvent","eventName":"select","itemID":15,"timeOfEvent":1601386463622,"eventDuration":0},{"category":"mouseEvent","eventName":"firstHover","itemID":15,"timeOfEvent":1601386466467,"eventDuration":6959},{"category":"mouseEvent","eventName":"firstHover","itemID":16,"timeOfEvent":1601386468824,"eventDuration":2300},{"category":"mouseEvent","eventName":"select","itemID":17,"timeOfEvent":1601386470927,"eventDuration":0},{"category":"mouseEvent","eventName":"longHover","itemID":17,"timeOfEvent":1601386471374,"eventDuration":2150},{"category":"mouseEvent","eventName":"select","itemID":14,"timeOfEvent":1601386472079,"eventDuration":0},{"category":"mouseEvent","eventName":"firstHover","itemID":14,"timeOfEvent":1601386472524,"eventDuration":1067},{"category":"mouseEvent","eventName":"firstHover","itemID":12,"timeOfEvent":1601386472591,"eventDuration":67},{"category":"mouseEvent","eventName":"select","itemID":12,"timeOfEvent":1601386473432,"eventDuration":0},{"category":"mouseEvent","eventName":"firstHover","itemID":12,"timeOfEvent":1601386473757,"eventDuration":813},{"category":"mouseEvent","eventName":"select","itemID":11,"timeOfEvent":1601386476114,"eventDuration":0},{"category":"mouseEvent","eventName":"fourthElementSelected","itemID":11,"timeOfEvent":1601386476114,"eventDuration":0},{"category":"mouseEvent","eventName":"firstHover","itemID":11,"timeOfEvent":1601386476540,"eventDuration":1849},{"category":"mouseEvent","eventName":"firstHover","itemID":20,"timeOfEvent":1601386476573,"eventDuration":33},{"category":"mouseEvent","eventName":"firstHover","itemID":20,"timeOfEvent":1601386478057,"eventDuration":767},{"category":"mouseEvent","eventName":"firstHover","itemID":11,"timeOfEvent":1601386478357,"eventDuration":300},{"category":"mouseEvent","eventName":"firstHover","itemID":20,"timeOfEvent":1601386478440,"eventDuration":67},{"category":"mouseEvent","eventName":"select","itemID":11,"timeOfEvent":1601386479121,"eventDuration":0},{"category":"mouseEvent","eventName":"fourthElementSelected","itemID":11,"timeOfEvent":1601386479121,"eventDuration":0},{"category":"mouseEvent","eventName":"firstHover","itemID":11,"timeOfEvent":1601386479706,"eventDuration":1250},{"category":"mouseEvent","eventName":"firstHover","itemID":20,"timeOfEvent":1601386479823,"eventDuration":100},{"category":"mouseEvent","eventName":"firstHover","itemID":20,"timeOfEvent":1601386480490,"eventDuration":91},{"category":"mouseEvent","eventName":"firstHover","itemID":12,"timeOfEvent":1601386480823,"eventDuration":299},{"category":"mouseEvent","eventName":"firstHover","itemID":20,"timeOfEvent":1601386483056,"eventDuration":16},{"category":"mouseEvent","eventName":"firstHover","itemID":20,"timeOfEvent":1601386485361,"eventDuration":7},{"category":"mouseEvent","eventName":"firstHover","itemID":14,"timeOfEvent":1601386486139,"eventDuration":749},{"category":"serverEvent","eventName":"loadNewRankingType","itemID":1,"timeOfEvent":1601386486564,"eventDuration":0},{"category":"rankingRepresentation","timeOfEvent":1601386486564,"ranking":[{"id":51,"name":"Ruth Cook","score":0.7770644320163811,"tag1":"98%","tag2":100,"tag3":1,"gender":"f","fairrank":1,"scorerank":1,"rank":1},{"id":59,"name":"Lisa Lewis","score":0.6948946293440471,"tag1":"100%","tag2":96,"tag3":0,"gender":"f","fairrank":9,"scorerank":6,"rank":2},{"id":55,"name":"Stephanie Anderson","score":0.7241151414444923,"tag1":"88%","tag2":100,"tag3":2,"gender":"f","fairrank":5,"scorerank":3,"rank":3},{"id":60,"name":"Barbara Wright","score":0.6912021464108199,"tag1":"100%","tag2":100,"tag3":0,"gender":"f","fairrank":10,"scorerank":7,"rank":4},{"id":54,"name":"Andrew Scott","score":0.6795129006315132,"tag1":"100%","tag2":83,"tag3":0,"gender":"m","fairrank":4,"scorerank":9,"rank":5},{"id":57,"name":"Nancy Adams","score":0.723664417490066,"tag1":"100%","tag2":100,"tag3":0,"gender":"f","fairrank":7,"scorerank":4,"rank":6},{"id":52,"name":"Joseph Scott","score":0.6889140819717308,"tag1":"100%","tag2":100,"tag3":0,"gender":"m","fairrank":2,"scorerank":8,"rank":7},{"id":58,"name":"Helen Hill","score":0.7190217755368232,"tag1":"100%","tag2":100,"tag3":0,"gender":"f","fairrank":8,"scorerank":5,"rank":8},{"id":53,"name":"Barbara Adams","score":0.7763590957966456,"tag1":"96%","tag2":100,"tag3":1,"gender":"f","fairrank":3,"scorerank":2,"rank":9},{"id":56,"name":"Michael Walker","score":0.6792422827330241,"tag1":"100%","tag2":95,"tag3":0,"gender":"m","fairrank":6,"scorerank":10,"rank":10}]},{"category":"mouseEvent","eventName":"firstHover","itemID":57,"timeOfEvent":1601386486690,"eventDuration":49},{"category":"mouseEvent","eventName":"firstHover","itemID":57,"timeOfEvent":1601386487357,"eventDuration":434},{"category":"mouseEvent","eventName":"firstHover","itemID":51,"timeOfEvent":1601386491441,"eventDuration":467},{"category":"mouseEvent","eventName":"firstHover","itemID":55,"timeOfEvent":1601386491924,"eventDuration":217},{"category":"mouseEvent","eventName":"select","itemID":54,"timeOfEvent":1601386492793,"eventDuration":0},{"category":"mouseEvent","eventName":"firstHover","itemID":54,"timeOfEvent":1601386494107,"eventDuration":2133},{"category":"mouseEvent","eventName":"select","itemID":52,"timeOfEvent":1601386494984,"eventDuration":0},{"category":"mouseEvent","eventName":"firstHover","itemID":52,"timeOfEvent":1601386495474,"eventDuration":1350},{"category":"mouseEvent","eventName":"firstHover","itemID":58,"timeOfEvent":1601386495925,"eventDuration":451},{"category":"mouseEvent","eventName":"select","itemID":56,"timeOfEvent":1601386498207,"eventDuration":0},{"category":"mouseEvent","eventName":"firstHover","itemID":56,"timeOfEvent":1601386499124,"eventDuration":1450},{"category":"mouseEvent","eventName":"firstHover","itemID":56,"timeOfEvent":1601386499490,"eventDuration":133},{"category":"mouseEvent","eventName":"firstHover","itemID":56,"timeOfEvent":1601386500274,"eventDuration":634},{"category":"mouseEvent","eventName":"firstHover","itemID":58,"timeOfEvent":1601386500490,"eventDuration":33},{"category":"mouseEvent","eventName":"firstHover","itemID":58,"timeOfEvent":1601386500940,"eventDuration":100},{"category":"mouseEvent","eventName":"select","itemID":53,"timeOfEvent":1601386501942,"eventDuration":0},{"category":"mouseEvent","eventName":"firstHover","itemID":53,"timeOfEvent":1601386502242,"eventDuration":1285},{"category":"timeStamps","eventName":"rankingOverallDuration","itemID":"none","timeOfEvent":1601386503848,"eventDuration":17286}],"survey":[{"category":"serverEvent","eventName":"loadSurveyQuestion","itemID":1,"timeOfEvent":1601386506364,"eventDuration":0},{"question":1,"answers":["4 trust-4"],"timeOfEvent":1601386510603,"category":"surveyQuestionAnswers"},{"category":"serverEvent","eventName":"loadSurveyQuestion","itemID":2,"timeOfEvent":1601386510604,"eventDuration":0},{"category":"mouseEvent","eventName":"firstHover","itemID":31,"timeOfEvent":1601386512023,"eventDuration":508},{"category":"mouseEvent","eventName":"firstHover","itemID":35,"timeOfEvent":1601386512090,"eventDuration":50},{"category":"mouseEvent","eventName":"firstHover","itemID":38,"timeOfEvent":1601386512423,"eventDuration":331},{"category":"mouseEvent","eventName":"firstHover","itemID":40,"timeOfEvent":1601386512478,"eventDuration":55},{"category":"mouseEvent","eventName":"firstHover","itemID":39,"timeOfEvent":1601386514373,"eventDuration":50},{"question":2,"answers":["4 movingAssistnace-tasks-4","4 movingAssistnace-reviews-4","4 movingAssistnace-reliable-4","4 movingAssistnace-gender-4"],"timeOfEvent":1601386529632,"category":"surveyQuestionAnswers"},{"category":"serverEvent","eventName":"loadSurveyQuestion","itemID":3,"timeOfEvent":1601386529632,"eventDuration":0},{"category":"mouseEvent","eventName":"firstHover","itemID":11,"timeOfEvent":1601386532990,"eventDuration":62},{"category":"mouseEvent","eventName":"firstHover","itemID":20,"timeOfEvent":1601386533055,"eventDuration":33},{"category":"mouseEvent","eventName":"firstHover","itemID":14,"timeOfEvent":1601386533105,"eventDuration":49},{"category":"mouseEvent","eventName":"firstHover","itemID":17,"timeOfEvent":1601386533122,"eventDuration":17},{"category":"mouseEvent","eventName":"firstHover","itemID":13,"timeOfEvent":1601386533172,"eventDuration":49},{"category":"mouseEvent","eventName":"firstHover","itemID":18,"timeOfEvent":1601386533255,"eventDuration":82},{"category":"mouseEvent","eventName":"firstHover","itemID":18,"timeOfEvent":1601386533506,"eventDuration":25},{"question":3,"answers":["4 eventStaffing-tasks-4","3 eventStaffing-reviews-3","4 eventStaffing-reliable-4","4 eventStaffing-gender-4"],"timeOfEvent":1601386539881,"category":"surveyQuestionAnswers"},{"category":"serverEvent","eventName":"loadSurveyQuestion","itemID":4,"timeOfEvent":1601386539881,"eventDuration":0},{"category":"mouseEvent","eventName":"firstHover","itemID":56,"timeOfEvent":1601386544656,"eventDuration":4097},{"category":"mouseEvent","eventName":"firstHover","itemID":58,"timeOfEvent":1601386544691,"eventDuration":34},{"category":"mouseEvent","eventName":"firstHover","itemID":57,"timeOfEvent":1601386544710,"eventDuration":19},{"category":"mouseEvent","eventName":"firstHover","itemID":60,"timeOfEvent":1601386544743,"eventDuration":33},{"question":4,"answers":["4 shopping-tasks-4","4 shopping-reviews-4","4 shopping-reliable-4","4 shopping-gender-4"],"timeOfEvent":1601386553313,"category":"surveyQuestionAnswers"},{"category":"serverEvent","eventName":"loadSurveyQuestion","itemID":5,"timeOfEvent":1601386553313,"eventDuration":0},{"question":5,"answers":["i must watch the persons personality and positive reviews and percentages then how their capacity."],"timeOfEvent":1601386629230,"category":"surveyQuestionAnswers"},{"category":"serverEvent","eventName":"loadSurveyQuestion","itemID":6,"timeOfEvent":1601386629231,"eventDuration":0},{"question":6,"answers":["male male","3544 3544","college college","60k89k 60k89k"],"timeOfEvent":1601386648027,"category":"surveyQuestionAnswers"},{"category":"btn","eventName":"finishedTest","itemID":"none","timeOfEvent":1601386648027,"eventDuration":1601386648027},{"category":"screenWidth","eventName":1024,"itemID":"none","timeOfEvent":1601386648027,"eventDuration":0},{"category":"timeStamps","eventName":"durationOverall","itemID":"none","timeOfEvent":1601386648027,"eventDuration":1601386648027}],"treatmentOrder":[0,1,2]}