{"briefing":[{"category":"briefingEvent","eventName":"displayBriefingStep","itemID":1,"timeOfEvent":1601761973781,"eventDuration":0},{"category":"briefingEvent","eventName":"displayBriefingStep","itemID":2,"timeOfEvent":1601761983966,"eventDuration":0},{"category":"briefingEvent","eventName":"displayBriefingStep","itemID":3,"timeOfEvent":1601761991617,"eventDuration":0},{"category":"briefingEvent","eventName":"displayBriefingStep","itemID":4,"timeOfEvent":1601762013758,"eventDuration":0},{"category":"briefingEvent","eventName":"displayBriefingStep","itemID":5,"timeOfEvent":1601762073209,"eventDuration":0},{"category":"briefingEvent","eventName":"displayBriefingStep","itemID":6,"timeOfEvent":1601762091778,"eventDuration":0},{"category":"timeStamps","eventName":"briefingDuration","itemID":"none","timeOfEvent":1601762156864,"eventDuration":null}],"ranking":[{"category":"serverEvent","eventName":"loadNewRankingType","itemID":2,"timeOfEvent":1601762157149,"eventDuration":0},{"category":"rankingRepresentation","timeOfEvent":1601762157149,"ranking":[{"id":21,"name":"Timothy Thomas","score":0.8685688011573159,"tag1":"99%","tag2":100,"tag3":634,"gender":"m","fairrank":1,"scorerank":1,"rank":1},{"id":23,"name":"Donald Hill","score":0.8590045381474498,"tag1":"97%","tag2":100,"tag3":395,"gender":"m","fairrank":3,"scorerank":2,"rank":2},{"id":25,"name":"Charles Brown","score":0.8502374704583605,"tag1":"100%","tag2":100,"tag3":64,"gender":"m","fairrank":5,"scorerank":3,"rank":3},{"id":22,"name":"Brenda Harris","score":0.8484922997440333,"tag1":"100%","tag2":100,"tag3":41,"gender":"f","fairrank":2,"scorerank":4,"rank":4},{"id":27,"name":"John Davis","score":0.8481191210673654,"tag1":"100%","tag2":100,"tag3":158,"gender":"m","fairrank":7,"scorerank":5,"rank":5},{"id":28,"name":"Anthony Anderson","score":0.8466832462421382,"tag1":"98%","tag2":100,"tag3":388,"gender":"m","fairrank":8,"scorerank":6,"rank":6},{"id":24,"name":"Lisa Green","score":0.839492387045522,"tag1":"100%","tag2":100,"tag3":141,"gender":"f","fairrank":4,"scorerank":7,"rank":7},{"id":29,"name":"Jacob Wright","score":0.8384138632702831,"tag1":"100%","tag2":98,"tag3":458,"gender":"m","fairrank":9,"scorerank":8,"rank":8},{"id":30,"name":"Ryan Morris","score":0.8371873144904489,"tag1":"100%","tag2":100,"tag3":48,"gender":"m","fairrank":10,"scorerank":9,"rank":9},{"id":26,"name":"Laura Thomas","score":0.8339155032920075,"tag1":"99%","tag2":100,"tag3":7,"gender":"f","fairrank":6,"scorerank":10,"rank":10}]},{"category":"mouseEvent","eventName":"firstHover","itemID":24,"timeOfEvent":1601762167118,"eventDuration":9948},{"category":"mouseEvent","eventName":"firstHover","itemID":27,"timeOfEvent":1601762167251,"eventDuration":116},{"category":"mouseEvent","eventName":"firstHover","itemID":25,"timeOfEvent":1601762167303,"eventDuration":16},{"category":"mouseEvent","eventName":"firstHover","itemID":30,"timeOfEvent":1601762213922,"eventDuration":51},{"category":"mouseEvent","eventName":"firstHover","itemID":29,"timeOfEvent":1601762213976,"eventDuration":54},{"category":"mouseEvent","eventName":"firstHover","itemID":28,"timeOfEvent":1601762214109,"eventDuration":99},{"category":"mouseEvent","eventName":"select","itemID":22,"timeOfEvent":1601762214383,"eventDuration":0},{"category":"mouseEvent","eventName":"unselect","itemID":22,"timeOfEvent":1601762215157,"eventDuration":0},{"category":"mouseEvent","eventName":"firstHover","itemID":22,"timeOfEvent":1601762215677,"eventDuration":1534},{"category":"mouseEvent","eventName":"firstHover","itemID":28,"timeOfEvent":1601762215778,"eventDuration":67},{"category":"mouseEvent","eventName":"firstHover","itemID":29,"timeOfEvent":1601762215844,"eventDuration":49},{"category":"mouseEvent","eventName":"firstHover","itemID":26,"timeOfEvent":1601762215912,"eventDuration":51},{"category":"mouseEvent","eventName":"firstHover","itemID":30,"timeOfEvent":1601762226904,"eventDuration":68},{"category":"mouseEvent","eventName":"firstHover","itemID":29,"timeOfEvent":1601762226953,"eventDuration":34},{"category":"mouseEvent","eventName":"firstHover","itemID":28,"timeOfEvent":1601762227021,"eventDuration":51},{"category":"mouseEvent","eventName":"firstHover","itemID":22,"timeOfEvent":1601762227103,"eventDuration":65},{"category":"mouseEvent","eventName":"firstHover","itemID":23,"timeOfEvent":1601762231641,"eventDuration":4486},{"category":"mouseEvent","eventName":"firstHover","itemID":23,"timeOfEvent":1601762249037,"eventDuration":117},{"category":"mouseEvent","eventName":"firstHover","itemID":22,"timeOfEvent":1601762249073,"eventDuration":36},{"category":"mouseEvent","eventName":"firstHover","itemID":28,"timeOfEvent":1601762249106,"eventDuration":18},{"category":"mouseEvent","eventName":"firstHover","itemID":29,"timeOfEvent":1601762249138,"eventDuration":32},{"category":"mouseEvent","eventName":"firstHover","itemID":26,"timeOfEvent":1601762249172,"eventDuration":34},{"category":"mouseEvent","eventName":"firstHover","itemID":30,"timeOfEvent":1601762260364,"eventDuration":50},{"category":"mouseEvent","eventName":"firstHover","itemID":24,"timeOfEvent":1601762260414,"eventDuration":34},{"category":"mouseEvent","eventName":"firstHover","itemID":27,"timeOfEvent":1601762260498,"eventDuration":67},{"category":"mouseEvent","eventName":"firstHover","itemID":25,"timeOfEvent":1601762260632,"eventDuration":118},{"category":"mouseEvent","eventName":"select","itemID":21,"timeOfEvent":1601762260894,"eventDuration":0},{"category":"mouseEvent","eventName":"firstHover","itemID":21,"timeOfEvent":1601762266802,"eventDuration":6121},{"category":"mouseEvent","eventName":"firstHover","itemID":25,"timeOfEvent":1601762267021,"eventDuration":185},{"category":"mouseEvent","eventName":"firstHover","itemID":27,"timeOfEvent":1601762267237,"eventDuration":183},{"category":"mouseEvent","eventName":"firstHover","itemID":24,"timeOfEvent":1601762267437,"eventDuration":149},{"category":"mouseEvent","eventName":"select","itemID":29,"timeOfEvent":1601762267863,"eventDuration":0},{"category":"mouseEvent","eventName":"firstHover","itemID":29,"timeOfEvent":1601762267989,"eventDuration":534},{"category":"mouseEvent","eventName":"select","itemID":28,"timeOfEvent":1601762268215,"eventDuration":0},{"category":"mouseEvent","eventName":"firstHover","itemID":28,"timeOfEvent":1601762268405,"eventDuration":400},{"category":"mouseEvent","eventName":"firstHover","itemID":24,"timeOfEvent":1601762268555,"eventDuration":100},{"category":"mouseEvent","eventName":"firstHover","itemID":30,"timeOfEvent":1601762268672,"eventDuration":67},{"category":"mouseEvent","eventName":"firstHover","itemID":30,"timeOfEvent":1601762291123,"eventDuration":85},{"category":"mouseEvent","eventName":"firstHover","itemID":24,"timeOfEvent":1601762291324,"eventDuration":167},{"category":"mouseEvent","eventName":"firstHover","itemID":27,"timeOfEvent":1601762291642,"eventDuration":261},{"category":"mouseEvent","eventName":"firstHover","itemID":22,"timeOfEvent":1601762291859,"eventDuration":167},{"category":"mouseEvent","eventName":"select","itemID":23,"timeOfEvent":1601762292704,"eventDuration":0},{"category":"mouseEvent","eventName":"firstHover","itemID":23,"timeOfEvent":1601762292959,"eventDuration":1033},{"category":"mouseEvent","eventName":"firstHover","itemID":25,"timeOfEvent":1601762293026,"eventDuration":67},{"category":"mouseEvent","eventName":"firstHover","itemID":27,"timeOfEvent":1601762293093,"eventDuration":50},{"category":"mouseEvent","eventName":"firstHover","itemID":24,"timeOfEvent":1601762293192,"eventDuration":83},{"category":"serverEvent","eventName":"loadNewRankingType","itemID":2,"timeOfEvent":1601762299238,"eventDuration":0},{"category":"rankingRepresentation","timeOfEvent":1601762299238,"ranking":[{"id":1,"name":"Kevin Thomas","score":0.799641978367866,"tag1":"95%","tag2":96,"tag3":0,"gender":"m","fairrank":1,"scorerank":1,"rank":1},{"id":3,"name":"Charles Lewis","score":0.788158103114649,"tag1":"98%","tag2":100,"tag3":1,"gender":"m","fairrank":3,"scorerank":2,"rank":2},{"id":5,"name":"Thomas Robinson","score":0.7805555452827792,"tag1":"100%","tag2":78,"tag3":0,"gender":"m","fairrank":5,"scorerank":3,"rank":3},{"id":7,"name":"Jacob White","score":0.7710606362667689,"tag1":"98%","tag2":100,"tag3":0,"gender":"m","fairrank":7,"scorerank":4,"rank":4},{"id":8,"name":"Gary Moore","score":0.742341028683199,"tag1":"100%","tag2":100,"tag3":6,"gender":"m","fairrank":8,"scorerank":5,"rank":5},{"id":2,"name":"Susan White","score":0.7412400221038719,"tag1":"98%","tag2":100,"tag3":10,"gender":"f","fairrank":2,"scorerank":6,"rank":6},{"id":9,"name":"Justin Thompson","score":0.7375636107859171,"tag1":"97%","tag2":100,"tag3":2,"gender":"m","fairrank":9,"scorerank":7,"rank":7},{"id":4,"name":"Amanda Jackson","score":0.7258889517568552,"tag1":"93%","tag2":100,"tag3":2,"gender":"f","fairrank":4,"scorerank":8,"rank":8},{"id":10,"name":"Stephen Campbell","score":0.719530008545884,"tag1":"99%","tag2":100,"tag3":2,"gender":"m","fairrank":10,"scorerank":9,"rank":9},{"id":6,"name":"Anna Moore","score":0.7030471958586693,"tag1":"100%","tag2":100,"tag3":3,"gender":"f","fairrank":6,"scorerank":10,"rank":10}]},{"category":"mouseEvent","eventName":"firstHover","itemID":10,"timeOfEvent":1601762320315,"eventDuration":135},{"category":"mouseEvent","eventName":"firstHover","itemID":6,"timeOfEvent":1601762320533,"eventDuration":218},{"category":"mouseEvent","eventName":"firstHover","itemID":4,"timeOfEvent":1601762320917,"eventDuration":267},{"category":"mouseEvent","eventName":"select","itemID":2,"timeOfEvent":1601762321268,"eventDuration":0},{"category":"mouseEvent","eventName":"firstHover","itemID":2,"timeOfEvent":1601762321735,"eventDuration":751},{"category":"mouseEvent","eventName":"select","itemID":8,"timeOfEvent":1601762322085,"eventDuration":0},{"category":"mouseEvent","eventName":"firstHover","itemID":8,"timeOfEvent":1601762325720,"eventDuration":3985},{"category":"mouseEvent","eventName":"firstHover","itemID":9,"timeOfEvent":1601762325804,"eventDuration":66},{"category":"mouseEvent","eventName":"firstHover","itemID":10,"timeOfEvent":1601762325854,"eventDuration":34},{"category":"mouseEvent","eventName":"firstHover","itemID":6,"timeOfEvent":1601762325888,"eventDuration":34},{"category":"mouseEvent","eventName":"select","itemID":6,"timeOfEvent":1601762327389,"eventDuration":0},{"category":"mouseEvent","eventName":"longHover","itemID":6,"timeOfEvent":1601762333110,"eventDuration":6889},{"category":"mouseEvent","eventName":"select","itemID":10,"timeOfEvent":1601762333532,"eventDuration":0},{"category":"mouseEvent","eventName":"firstHover","itemID":10,"timeOfEvent":1601762333878,"eventDuration":551},{"category":"serverEvent","eventName":"loadNewRankingType","itemID":2,"timeOfEvent":1601762334827,"eventDuration":0},{"category":"rankingRepresentation","timeOfEvent":1601762334827,"ranking":[{"id":41,"name":"Nicholas Williams","score":0.7770644320163811,"tag1":"98%","tag2":100,"tag3":1,"gender":"m","fairrank":1,"scorerank":1,"rank":1},{"id":43,"name":"David Clark","score":0.7763590957966456,"tag1":"96%","tag2":100,"tag3":1,"gender":"m","fairrank":3,"scorerank":2,"rank":2},{"id":45,"name":"Brandon Cook","score":0.7241151414444923,"tag1":"88%","tag2":100,"tag3":2,"gender":"m","fairrank":5,"scorerank":3,"rank":3},{"id":47,"name":"Thomas Allen","score":0.723664417490066,"tag1":"100%","tag2":100,"tag3":0,"gender":"m","fairrank":7,"scorerank":4,"rank":4},{"id":48,"name":"George Williams","score":0.7190217755368232,"tag1":"100%","tag2":100,"tag3":0,"gender":"m","fairrank":8,"scorerank":5,"rank":5},{"id":49,"name":"Charles Evans","score":0.6948946293440471,"tag1":"100%","tag2":96,"tag3":0,"gender":"m","fairrank":9,"scorerank":6,"rank":6},{"id":50,"name":"George Hill","score":0.6912021464108199,"tag1":"100%","tag2":100,"tag3":0,"gender":"m","fairrank":10,"scorerank":7,"rank":7},{"id":42,"name":"Shirley Robinson","score":0.6889140819717308,"tag1":"100%","tag2":100,"tag3":0,"gender":"f","fairrank":2,"scorerank":8,"rank":8},{"id":44,"name":"Patricia Lewis","score":0.6795129006315132,"tag1":"100%","tag2":83,"tag3":0,"gender":"f","fairrank":4,"scorerank":9,"rank":9},{"id":46,"name":"Cynthia Walker","score":0.6792422827330241,"tag1":"100%","tag2":95,"tag3":0,"gender":"f","fairrank":6,"scorerank":10,"rank":10}]},{"category":"mouseEvent","eventName":"firstHover","itemID":50,"timeOfEvent":1601762347973,"eventDuration":18},{"category":"mouseEvent","eventName":"firstHover","itemID":44,"timeOfEvent":1601762348022,"eventDuration":49},{"category":"mouseEvent","eventName":"firstHover","itemID":50,"timeOfEvent":1601762358148,"eventDuration":34},{"category":"mouseEvent","eventName":"firstHover","itemID":48,"timeOfEvent":1601762358232,"eventDuration":68},{"category":"mouseEvent","eventName":"firstHover","itemID":45,"timeOfEvent":1601762358399,"eventDuration":133},{"category":"mouseEvent","eventName":"select","itemID":41,"timeOfEvent":1601762358619,"eventDuration":0},{"category":"mouseEvent","eventName":"firstHover","itemID":41,"timeOfEvent":1601762358865,"eventDuration":433},{"category":"mouseEvent","eventName":"select","itemID":43,"timeOfEvent":1601762359078,"eventDuration":0},{"category":"mouseEvent","eventName":"firstHover","itemID":43,"timeOfEvent":1601762359233,"eventDuration":368},{"category":"mouseEvent","eventName":"longHover","itemID":45,"timeOfEvent":1601762383217,"eventDuration":23984},{"category":"mouseEvent","eventName":"firstHover","itemID":48,"timeOfEvent":1601762383285,"eventDuration":51},{"category":"mouseEvent","eventName":"firstHover","itemID":50,"timeOfEvent":1601762384221,"eventDuration":936},{"category":"mouseEvent","eventName":"firstHover","itemID":50,"timeOfEvent":1601762394445,"eventDuration":51},{"category":"mouseEvent","eventName":"firstHover","itemID":48,"timeOfEvent":1601762394546,"eventDuration":85},{"category":"mouseEvent","eventName":"firstHover","itemID":45,"timeOfEvent":1601762394712,"eventDuration":133},{"category":"mouseEvent","eventName":"firstHover","itemID":41,"timeOfEvent":1601762394879,"eventDuration":117},{"category":"mouseEvent","eventName":"select","itemID":45,"timeOfEvent":1601762395390,"eventDuration":0},{"category":"mouseEvent","eventName":"firstHover","itemID":45,"timeOfEvent":1601762395530,"eventDuration":584},{"category":"mouseEvent","eventName":"firstHover","itemID":48,"timeOfEvent":1601762395581,"eventDuration":34},{"category":"mouseEvent","eventName":"select","itemID":50,"timeOfEvent":1601762406163,"eventDuration":0},{"category":"mouseEvent","eventName":"firstHover","itemID":50,"timeOfEvent":1601762406289,"eventDuration":334},{"category":"timeStamps","eventName":"rankingOverallDuration","itemID":"none","timeOfEvent":1601762407040,"eventDuration":72213}],"survey":[{"category":"serverEvent","eventName":"loadSurveyQuestion","itemID":1,"timeOfEvent":1601762407212,"eventDuration":0},{"question":1,"answers":["4 trust-4"],"timeOfEvent":1601762411577,"category":"surveyQuestionAnswers"},{"category":"serverEvent","eventName":"loadSurveyQuestion","itemID":2,"timeOfEvent":1601762411577,"eventDuration":0},{"category":"mouseEvent","eventName":"firstHover","itemID":49,"timeOfEvent":1601762418799,"eventDuration":7167},{"category":"mouseEvent","eventName":"firstHover","itemID":42,"timeOfEvent":1601762418850,"eventDuration":50},{"category":"mouseEvent","eventName":"firstHover","itemID":46,"timeOfEvent":1601762419505,"eventDuration":638},{"question":2,"answers":["5 movingAssistnace-tasks-5","5 movingAssistnace-reviews-5","5 movingAssistnace-reliable-5","3 movingAssistnace-gender-3"],"timeOfEvent":1601762428828,"category":"surveyQuestionAnswers"},{"category":"serverEvent","eventName":"loadSurveyQuestion","itemID":3,"timeOfEvent":1601762428828,"eventDuration":0},{"question":3,"answers":["5 eventStaffing-tasks-5","5 eventStaffing-reviews-5","5 eventStaffing-reliable-5","2 eventStaffing-gender-2"],"timeOfEvent":1601762499478,"category":"surveyQuestionAnswers"},{"category":"serverEvent","eventName":"loadSurveyQuestion","itemID":4,"timeOfEvent":1601762499478,"eventDuration":0},{"question":4,"answers":["5 shopping-tasks-5","5 shopping-reviews-5","5 shopping-reliable-5","1 shopping-gender-1"],"timeOfEvent":1601762506657,"category":"surveyQuestionAnswers"},{"category":"serverEvent","eventName":"loadSurveyQuestion","itemID":5,"timeOfEvent":1601762506657,"eventDuration":0},{"question":5,"answers":["I wanted people who had more experience in the individual task category so I looked at that first. Then I looked at reliability and positive reviews. If someone didn't have experience in that task then I relied on reviews and reliability only. For the moving one, I chose a man over a woman for my fourth selection, even though they had the same statistics."],"timeOfEvent":1601762603101,"category":"surveyQuestionAnswers"},{"category":"serverEvent","eventName":"loadSurveyQuestion","itemID":6,"timeOfEvent":1601762603101,"eventDuration":0},{"question":6,"answers":["female female","3544 3544","master master","10k29k 10k29k"],"timeOfEvent":1601762612217,"category":"surveyQuestionAnswers"},{"category":"btn","eventName":"finishedTest","itemID":"none","timeOfEvent":1601762612217,"eventDuration":1601762612217},{"category":"screenWidth","eventName":1680,"itemID":"none","timeOfEvent":1601762612217,"eventDuration":0},{"category":"timeStamps","eventName":"durationOverall","itemID":"none","timeOfEvent":1601762612217,"eventDuration":1601762612217}],"treatmentOrder":[1,2,0]}